Metadata-Version: 2.1
Name: friendtech
Version: 0.1.0
Summary: A python module for friend.tech
Author: ItsAditya (https://itsaditya.xyz)
Author-email: <chaudharyaditya0005@gmail.com>
Keywords: friend.tech,social media,crypto,decentralized social media
Classifier: Development Status :: 1 - Planning
Classifier: Intended Audience :: Developers
Classifier: Programming Language :: Python :: 3
Classifier: Operating System :: Unix
Classifier: Operating System :: MacOS :: MacOS X
Classifier: Operating System :: Microsoft :: Windows
